{
  "version": "7",
  "dialect": "postgresql",
  "entries": [
    {
      "idx": 0,
      "version": "7",
      "when": 1735907879539,
      "tag": "0000_cheerful_hellfire_club",
      "breakpoints": true
    },
    {
      "idx": 1,
      "version": "7",
      "when": 1736028733158,
      "tag": "0001_dashing_silhouette",
      "breakpoints": true
    },
    {
      "idx": 2,
      "version": "7",
      "when": 1736029998375,
      "tag": "0002_flowery_gateway",
      "breakpoints": true
    }
  ]
}